{
  "africa": "châu Phi",
  "airport": "sân bay",
  "alien": "người ngoài hành tinh",
  "america": "châu Mỹ",
  "angry": "tức giận",
  "animals": "động vật",
  "ant": "con kiến",
  "antarctica": "châu Nam Cực",
  "apartment": "căn hộ",
  "apple": "quả táo",
  "arm": "cánh tay",
  "armchair": "ghế bành",
  "artist": "nghệ sĩ",
  "asia": "châu Á",
  "astronaut": "phi hành gia",
  "australia": "châu Úc",
  "baby": "em bé",
  "badminton": "cầu lông",
  "bakery": "tiệm bánh",
  "balcony": "ban công",
  "balloon": "bóng bay",
  "bank": "ngân hàng",
  "barn": "nhà kho",
  "baseball": "bóng chày",
  "basketball": "bóng rổ",
  "bat": "con dơi",
  "bathroom": "phòng tắm",
  "bean": "hạt đậu",
  "beans": "các loại đậu",
  "bear": "con gấu",
  "beautiful": "xinh đẹp",
  "bedroom": "phòng ngủ",
  "bee": "con ong",
  "bellpepper": "ớt chuông",
  "belt": "thắt lưng",
  "big": "to",
  "bin": "thùng rác",
  "bird": "con chim",
  "boardgames": "trò chơi bàn cờ",
  "book": "quyển sách",
  "bookcase": "giá sách",
  "bookstore": "nhà sách",
  "boots": "ủng",
  "bougainvillea": "hoa giấy",
  "brazil": "Brazil",
  "breakfast": "bữa sáng",
  "broccoli": "bông cải xanh",
  "broom": "cái chổi",
  "brother": "anh trai",
  "burger": "bánh burger",
  "busstop": "trạm xe buýt",
  "butterfly": "con bướm",
  "cabbage": "bắp cải",
  "calculator": "máy tính",
  "calf": "bê con",
  "cambodia": "Campuchia",
  "camel": "con lạc đà",
  "canada": "Canada",
  "carrot": "cà rốt",
  "cat": "con mèo",
  "caterpillar": "sâu bướm",
  "cave": "hang động",
  "champagne": "sâm panh",
  "chick": "gà con",
  "chicken": "con gà",
  "child": "đứa trẻ",
  "children": "trẻ em",
  "china": "Trung Quốc",
  "chips": "khoai tây chiên",
  "chocolate": "sô cô la",
  "cinema": "rạp chiếu phim",
  "clean": "sạch sẽ",
  "clock": "đồng hồ",
  "cloud": "đám mây",
  "cloudy": "nhiều mây",
  "coat": "áo khoác",
  "coconut": "quả dừa",
  "cocoon": "kén",
  "cold": "lạnh",
  "computer": "máy tính",
  "confetti": "giấy kim tuyến",
  "cook": "nấu ăn",
  "cool": "mát mẻ",
  "coop": "chuồng gà",
  "coral": "san hô",
  "corn": "ngô",
  "crocodile": "cá sấu",
  "cry": "khóc",
  "cucumber": "dưa chuột",
  "daisy": "hoa cúc",
  "decorate": "trang trí",
  "dictionary": "từ điển",
  "diningroom": "phòng ăn",
  "dinner": "bữa tối",
  "dirty": "bẩn",
  "doctor": "bác sĩ",
  "dolphin": "cá heo",
  "dove": "chim bồ câu",
  "dragondance": "múa rồng",
  "dragonfly": "chuồn chuồn",
  "draw": "vẽ",
  "dress": "váy",
  "drink": "uống",
  "dry": "khô",
  "duck": "con vịt",
  "ear": "tai",
  "egg": "quả trứng",
  "eggplant": "cà tím",
  "eggs": "trứng",
  "elf": "tiên nhỏ",
  "eraser": "cục tẩy",
  "europe": "châu Âu",
  "eye": "mắt",
  "eyes": "đôi mắt",
  "face": "khuôn mặt",
  "fan": "quạt",
  "farmer": "nông dân",
  "favourite": "yêu thích",
  "feed": "cho ăn",
  "fence": "hàng rào",
  "fig": "quả sung",
  "finger": "ngón tay",
  "firestation": "trạm cứu hỏa",
  "firework": "pháo hoa",
  "fish": "con cá",
  "fishing": "câu cá",
  "flat": "căn hộ",
  "flock": "đàn",
  "flower": "hoa",
  "fly": "bay",
  "folder": "thư mục",
  "foot": "bàn chân",
  "football": "bóng đá",
  "forest": "rừng",
  "fox": "con cáo",
  "france": "Pháp",
  "fridge": "tủ lạnh",
  "fullcaterpillar": "sâu bướm hoàn chỉnh",
  "funny": "vui nhộn",
  "garage": "ga ra",
  "garden": "vườn",
  "garlic": "tỏi",
  "germany": "Đức",
  "gift": "món quà",
  "ginger": "gừng",
  "gingerbread": "bánh gừng",
  "giraffe": "hươu cao cổ",
  "gloves": "găng tay",
  "gotobed": "đi ngủ",
  "gotoschool": "đi học",
  "gotothepagoda": "đi chùa",
  "gorilla": "khỉ đột",
  "grapes": "nho",
  "guitar": "đàn guitar",
  "hair": "tóc",
  "hand": "bàn tay",
  "handbag": "túi xách",
  "hat": "mũ",
  "havebath": "tắm bồn",
  "havebreakfast": "ăn sáng",
  "havedinner": "ăn tối",
  "havelunch": "ăn trưa",
  "head": "đầu",
  "hear": "nghe",
  "helicopter": "trực thăng",
  "hippo": "hà mã",
  "hockey": "khúc côn cầu",
  "hold": "cầm",
  "hospital": "bệnh viện",
  "hot": "nóng",
  "hotel": "khách sạn",
  "house": "ngôi nhà",
  "huladance": "điệu nhảy hula",
  "hungry": "đói",
  "ice": "đá",
  "icecream": "kem",
  "indonesia": "Indonesia",
  "island": "hòn đảo",
  "italy": "Ý",
  "jacket": "áo khoác",
  "jeans": "quần jean",
  "jellyfish": "con sứa",
  "juice": "nước ép",
  "kangaroo": "chuột túi",
  "kayaking": "chèo thuyền kayak",
  "keyboard": "bàn phím",
  "kick": "đá",
  "kitchen": "nhà bếp",
  "kite": "con diều",
  "kiwi": "quả kiwi",
  "knee": "đầu gối",
  "koala": "gấu koala",
  "labybug": "bọ rùa",
  "lamp": "đèn",
  "land": "đất liền",
  "lavender": "hoa oải hương",
  "leaf": "lá cây",
  "leg": "chân",
  "lesson": "bài học",
  "library": "thư viện",
  "lightning": "tia chớp",
  "lily": "hoa ly",
  "lime": "quả chanh xanh",
  "lion": "sư tử",
  "listentomusic": "nghe nhạc",
  "lizard": "thằn lằn",
  "lobster": "tôm hùm",
  "lotus": "hoa sen",
  "love": "yêu",
  "luckymoney": "lì xì",
  "lunch": "bữa trưa",
  "makecakes": "làm bánh",
  "man": "đàn ông",
  "mango": "xoài",
  "marigold": "hoa cúc vạn thọ",
  "marker": "bút lông",
  "market": "chợ",
  "mat": "thảm",
  "meal": "bữa ăn",
  "meatball": "thịt viên",
  "men": "đàn ông",
  "mercury": "sao Thủy",
  "metal": "kim loại",
  "mexico": "Mexico",
  "milk": "sữa",
  "mom": "mẹ",
  "moon": "mặt trăng",
  "mosquito": "muỗi",
  "mouse": "chuột",
  "mouth": "miệng",
  "museum": "bảo tàng",
  "mushroom": "nấm",
  "neck": "cổ",
  "neptune": "sao Hải Vương",
  "nervous": "lo lắng",
  "northamerica": "Bắc Mỹ",
  "nose": "mũi",
  "nurse": "y tá",
  "octopus": "bạch tuộc",
  "office": "văn phòng",
  "old": "già",
  "onion": "hành tây",
  "orange": "quả cam",
  "ostrich": "đà điểu",
  "ox": "con bò đực",
  "page": "trang sách",
  "paint": "tô màu",
  "painting": "bức tranh",
  "panda": "gấu trúc",
  "pants": "quần dài",
  "papaya": "đu đủ",
  "paper": "giấy",
  "park": "công viên",
  "partyhat": "mũ tiệc",
  "peacock": "con công",
  "pear": "quả lê",
  "pen": "bút mực",
  "pencilcase": "hộp bút",
  "people": "mọi người",
  "person": "người",
  "pharmacy": "nhà thuốc",
  "piano": "đàn piano",
  "picture": "bức tranh",
  "piglet": "heo con",
  "pilot": "phi công",
  "pineapple": "dứa",
  "plastic": "nhựa",
  "plum": "mận",
  "plumeria": "hoa sứ",
  "polarbear": "gấu Bắc Cực",
  "police": "cảnh sát",
  "policestation": "đồn cảnh sát",
  "pony": "ngựa con",
  "postoffice": "bưu điện",
  "poster": "áp phích",
  "potato": "khoai tây",
  "puton": "mặc vào",
  "putonclothes": "mặc quần áo",
  "rabbit": "con thỏ",
  "raccoon": "gấu mèo",
  "rainbow": "cầu vồng",
  "raincoat": "áo mưa",
  "rainy": "mưa",
  "rat": "chuột cống",
  "read": "đọc",
  "readstories": "đọc truyện",
  "receiveluckymoney": "nhận lì xì",
  "rhino": "tê giác",
  "rice": "cơm",
  "ride": "đi xe",
  "robot": "rô bốt",
  "rooster": "gà trống",
  "rose": "hoa hồng",
  "rubber": "cao su",
  "rug": "thảm",
  "ruler": "thước kẻ",
  "run": "chạy",
  "russia": "Nga",
  "sad": "buồn",
  "sail": "đi thuyền buồm",
  "sailing": "chèo thuyền buồm",
  "sandcastle": "lâu đài cát",
  "sausage": "xúc xích",
  "scared": "sợ hãi",
  "scarf": "khăn quàng cổ",
  "scientist": "nhà khoa học",
  "sealion": "sư tử biển",
  "seahorse": "cá ngựa",
  "shark": "cá mập",
  "sharpener": "gọt bút chì",
  "sheep": "con cừu",
  "shell": "vỏ sò",
  "ship": "tàu thủy",
  "shirt": "áo sơ mi",
  "shoes": "giày",
  "shop": "cửa hàng",
  "shoppingmall": "trung tâm mua sắm",
  "shorts": "quần đùi",
  "shoulder": "vai",
  "shrimp": "tôm",
  "shy": "rụt rè",
  "sick": "ốm",
  "silly": "ngốc nghếch",
  "singasong": "hát một bài hát",
  "singapore": "Singapore",
  "singer": "ca sĩ",
  "skateboard": "ván trượt",
  "skin": "da",
  "skirt": "váy",
  "sky": "bầu trời",
  "sleep": "ngủ",
  "sleepy": "buồn ngủ",
  "sleigh": "xe trượt tuyết",
  "slow": "chậm",
  "small": "nhỏ",
  "smell": "ngửi",
  "smile": "mỉm cười",
  "snorkeling": "lặn ống thở",
  "snowy": "có tuyết",
  "soap": "xà phòng",
  "socks": "tất",
  "song": "bài hát",
  "southamerica": "Nam Mỹ",
  "spain": "Tây Ban Nha",
  "sparrow": "chim sẻ",
  "spider": "con nhện",
  "sport": "thể thao",
  "squid": "mực",
  "starfish": "sao biển",
  "station": "nhà ga",
  "stem": "thân cây",
  "stickyricecake": "bánh chưng",
  "stingray": "cá đuối",
  "stocking": "tất dài",
  "strawberry": "dâu tây",
  "submarine": "tàu ngầm",
  "subway": "tàu điện ngầm",
  "summer": "mùa hè",
  "sunbathe": "tắm nắng",
  "sunglasses": "kính râm",
  "supermarket": "siêu thị",
  "surfing": "lướt sóng",
  "surprised": "ngạc nhiên",
  "swan": "thiên nga",
  "sweater": "áo len",
  "swim": "bơi",
  "swimsuit": "đồ bơi",
  "tshirt": "áo thun",
  "tabletennis": "bóng bàn",
  "tablet": "máy tính bảng",
  "tail": "đuôi",
  "takeashower": "tắm vòi sen",
  "takeoff": "cởi ra",
  "taste": "nếm",
  "teacher": "giáo viên",
  "telephone": "điện thoại",
  "tennis": "quần vợt",
  "thunder": "sấm",
  "tired": "mệt",
  "toe": "ngón chân",
  "tomato": "cà chua",
  "tomatoes": "cà chua",
  "toothbrush": "bàn chải đánh răng",
  "touch": "chạm",
  "towel": "khăn tắm",
  "train": "tàu hỏa",
  "trash": "rác",
  "tree": "cây",
  "truck": "xe tải",
  "tulip": "hoa tulip",
  "tv": "ti vi",
  "ugly": "xấu xí",
  "uncle": "chú",
  "uniform": "đồng phục",
  "vet": "bác sĩ thú y",
  "vietnam": "Việt Nam",
  "wall": "bức tường",
  "wash": "rửa",
  "washmyhand": "rửa tay",
  "watch": "xem",
  "watchfireworks": "xem pháo hoa",
  "watchtv": "xem ti vi",
  "water": "nước",
  "waterfall": "thác nước",
  "watermelon": "dưa hấu",
  "wear": "mặc",
  "whale": "cá voi",
  "window": "cửa sổ",
  "windsurfing": "lướt ván buồm",
  "windy": "nhiều gió",
  "winter": "mùa đông",
  "wolf": "con sói",
  "woman": "phụ nữ",
  "women": "phụ nữ",
  "wreath": "vòng hoa",
  "young": "trẻ",
  "zebra": "ngựa vằn",
  "zoo": "sở thú"
}
